loader/bin/loader.so
mklml_lnx_2018.0.1.20171227/lib/libiomp5.so
mklml_lnx_2018.0.1.20171227/lib/libmklml_gnu.so
mklml_lnx_2018.0.1.20171227/lib/libmklml_intel.so
neon/__init__.py
neon/version.py
neon/backends/__init__.py
neon/backends/abstract_backend.py
neon/backends/autodiff.py
neon/backends/backend.py
neon/backends/conv_kernel_test.py
neon/backends/convnet-benchmarks.py
neon/backends/convolution.py
neon/backends/cuda_batchnorm.py
neon/backends/cuda_templates.py
neon/backends/float_ew.py
neon/backends/kernel_specs.py
neon/backends/layer_cpu.py
neon/backends/layer_gpu.py
neon/backends/layer_mkl.py
neon/backends/math_cpu.py
neon/backends/nervanacpu.py
neon/backends/nervanagpu.py
neon/backends/nervanamkl.py
neon/backends/winograd.py
neon/backends/winograd4.py
neon/backends/winograd5.py
neon/backends/winograd_conv.py
neon/backends/kernels/__init__.py
neon/backends/kernels/cuda/__init__.py
neon/backends/kernels/cuda/binary.py
neon/backends/kernels/cuda/convolution.py
neon/backends/kernels/cuda/lookuptable.py
neon/backends/kernels/cuda/nms.py
neon/backends/kernels/cuda/pooling.py
neon/backends/kernels/cuda/roipooling.py
neon/backends/kernels/maxas/maxas.pl
neon/backends/kernels/maxas/MaxAs/Cubin.pm
neon/backends/kernels/maxas/MaxAs/MaxAs.pm
neon/backends/kernels/maxas/MaxAs/MaxAsGrammar.pm
neon/backends/kernels/sass/hconv_bprop_C1_N64.sass
neon/backends/kernels/sass/hconv_updat_C128_K128.sass
neon/backends/kernels/sass/hconv_updat_C128_K64.sass
neon/backends/kernels/sass/hconv_xprop_X128_N128.sass
neon/backends/kernels/sass/hconv_xprop_X128_N64.sass
neon/backends/kernels/sass/hconv_xprop_X32_N128.sass
neon/backends/kernels/sass/hconv_xprop_X64_N128.sass
neon/backends/kernels/sass/hconv_xprop_X64_N64.sass
neon/backends/kernels/sass/hgemm_common_128x128.sass
neon/backends/kernels/sass/hgemm_common_128x32.sass
neon/backends/kernels/sass/hgemm_common_128x64.sass
neon/backends/kernels/sass/hgemm_common_32x128.sass
nervananeon-2.6.0.dist-info/DESCRIPTION.rst
nervananeon-2.6.0.dist-info/METADATA
nervananeon-2.6.0.dist-info/RECORD
nervananeon-2.6.0.dist-info/WHEEL
nervananeon-2.6.0.dist-info/metadata.json
nervananeon-2.6.0.dist-info/top_level.txt
