Metadata-Version: 2.0
Name: nervananeon
Version: 2.6.0
Summary: Intel's deep learning framework
Home-page: http://www.intelnervana.com
Author: Intel Deep Learning System
Author-email: intelnervana@intel.com
License: License :: OSI Approved :: Apache Software License
Platform: UNKNOWN
Classifier: Development Status :: 3 - Alpha
Classifier: Environment :: Console
Classifier: Environment :: Console :: Curses
Classifier: Environment :: Web Environment
Classifier: Intended Audience :: End Users/Desktop
Classifier: Intended Audience :: Developers
Classifier: Intended Audience :: Science/Research
Classifier: License :: OSI Approved :: Apache Software License
Classifier: Operating System :: POSIX
Classifier: Operating System :: MacOS :: MacOS X
Classifier: Programming Language :: Python :: 2
Classifier: Programming Language :: Python :: 3
Classifier: Topic :: Scientific/Engineering :: Artificial Intelligence
Classifier: Topic :: Scientific/Engineering :: Information Analysis
Classifier: Topic :: System :: Distributed Computing
Requires-Dist: configargparse
Requires-Dist: numpy
Requires-Dist: pyyaml
Requires-Dist: pep8
Requires-Dist: flake8
Requires-Dist: pytest
Requires-Dist: pytest-cov
Requires-Dist: pytest-mock
Requires-Dist: posix-ipc
Requires-Dist: pillow
Requires-Dist: pylint
Requires-Dist: sphinx
Requires-Dist: h5py
Requires-Dist: appdirs
Requires-Dist: future
Requires-Dist: tqdm
Requires-Dist: cffi
Requires-Dist: filelock
Requires-Dist: py-cpuinfo
Requires-Dist: pypandoc
Requires-Dist: pandoc
